mllibs/__init__.py
mllibs/converters.py
mllibs/data_conversion.py
mllibs/df_helper.py
mllibs/dict_helper.py
mllibs/interface.py
mllibs/list_helper.py
mllibs/ner_activecolumn.py
mllibs/ner_source.py
mllibs/nerparser.py
mllibs/nlpi.py
mllibs/nlpm.py
mllibs/str_helper.py
mllibs/tokenisers.py
mllibs/corpus/classifier_subset.csv
mllibs/corpus/generative_corpus.csv
mllibs/corpus/ner_corpus.csv
mllibs/corpus/ner_mp.csv
mllibs/corpus/reference_database.csv
mllibs/corpus/wordlist.10000.txt
mllibs/eda/__init__.py
mllibs/eda/meda_pplot.json
mllibs/eda/meda_pplot.py
mllibs/eda/meda_scplot.json
mllibs/eda/meda_scplot.py
mllibs/eda/meda_splot.json
mllibs/eda/meda_splot.py
mllibs/libop/__init__.py
mllibs/libop/mlibop.json
mllibs/libop/mlibop.py
mllibs/nlp/__init__.py
mllibs/nlp/membedding.json
mllibs/nlp/membedding.py
mllibs/nlp/mencoder.json
mllibs/nlp/mencoder.py
mllibs/nlp/mtextnorm.json
mllibs/nlp/mtextnorm.py
mllibs/pd/__init__.py
mllibs/pd/mpd_df.json
mllibs/pd/mpd_df.py
mllibs/pd/mpd_talktodata.json
mllibs/pd/mpd_talktodata.py
mllibs/signal/__init__.py
mllibs/signal/mfourier_all.json
mllibs/signal/mfourier_all.py
mllibs/stats/__init__.py
mllibs/stats/mstats_plot.json
mllibs/stats/mstats_plot.py
mllibs/stats/mstats_tests.json
mllibs/stats/mstats_tests.py
mllibs-0.2.0.dist-info/LICENSE
mllibs-0.2.0.dist-info/METADATA
mllibs-0.2.0.dist-info/WHEEL
mllibs-0.2.0.dist-info/top_level.txt
mllibs-0.2.0.dist-info/RECORD
