Metadata-Version: 2.1
Name: mllibs
Version: 0.2.0
Summary: Simplifying Machine Learning
Home-page: https://github.com/shtrausslearning/mllibs
Author: Andrey Shtrauss
Author-email: shtraussart@gmail.com
Project-URL: Bug Tracker, https://github.com/shtrausslearning/mllibs/issues
Classifier: Programming Language :: Python :: 3
Classifier: License :: OSI Approved :: MIT License
Classifier: Operating System :: OS Independent
Requires-Python: >=3.7
License-File: LICENSE
Requires-Dist: requests
Requires-Dist: setuptools
Requires-Dist: wheel
Requires-Dist: numpy
Requires-Dist: pandas
Requires-Dist: scipy
Requires-Dist: nltk
Requires-Dist: seaborn
Requires-Dist: matplotlib
Requires-Dist: scikit-learn
Requires-Dist: gensim
Requires-Dist: spacy
Requires-Dist: torch
Requires-Dist: tensorflow
Requires-Dist: keras
Requires-Dist: statsmodels
Requires-Dist: pingouin
Requires-Dist: arch
Requires-Dist: transformers
Requires-Dist: urllib3 <2
Requires-Dist: catboost
